LICENSE
README.md
setup.py
dinkum/__init__.py
dinkum/dinkum.py
dinkum/dinkum_ascii_generate.py
dinkum/dinkum_ascii_reader.py
dinkum/dinkum_dbd.py
dinkum/dinkum_functions.py
dinkum/utils.py
dinkum.egg-info/PKG-INFO
dinkum.egg-info/SOURCES.txt
dinkum.egg-info/dependency_links.txt
dinkum.egg-info/requires.txt
dinkum.egg-info/top_level.txt
dinkum.egg-info/zip-safe
test/__init__.py
test/dinkum/__init__.py
test/dinkum/tests.py
test/resource/__init__.py
test/resource/raw/__init__.py
test/resource/raw/cache/__init__.py
version/__init__.py