Metadata-Version: 2.1
Name: dinkum
Version: 1.0.4
Summary: Some functions for interacting with [destmn]bd files in Python. Intent is to return a usable data object.
Home-page: https://ceotr.ocean.dal.ca/
Author: pye, Sean
Author-email: 
License: GNU General Public License v3 (GPLv3)
Requires-Python: >=3.8
License-File: LICENSE
